{"user_info": ["https://avatars1.githubusercontent.com/u/36975374?v=4", "개발 잘 하고 싶다\r\n", "Daejeon", "https://github.com/Jung-Woo-sik", "https://sites.google.com/cs-cnu.org/o0o0-sik/home", "Chung-nam National University"], "repo_names": {"0": "Areum_internship", "1": "CNU-assistant", "2": "CNU_assignment", "3": "CNU_graduation_project", "4": "CNU_Lab_Study", "5": "code", "6": "cryptozombie", "7": "Data_analysis_ethereum", "8": "ethereum_dApp", "9": "github_test", "10": "hyper", "11": "mailprograming_problem", "12": "PyTorch-FastCampus"}, "repo_info": [[3, "https://github.com/Jung-Woo-sik/Areum_internship"], [11, "https://github.com/Jung-Woo-sik/CNU-assistant"], [5, "https://github.com/Jung-Woo-sik/CNU_assignment"], [3, "https://github.com/Jung-Woo-sik/CNU_graduation_project"], [8, "https://github.com/Jung-Woo-sik/CNU_Lab_Study"], [3, "https://github.com/Jung-Woo-sik/code"], [1, "https://github.com/Jung-Woo-sik/cryptozombie"], [6, "https://github.com/Jung-Woo-sik/Data_analysis_ethereum"], [2, "https://github.com/Jung-Woo-sik/ethereum_dApp"], [1, "https://github.com/Jung-Woo-sik/github_test"], [3, "https://github.com/Jung-Woo-sik/hyper"], [46, "https://github.com/Jung-Woo-sik/mailprograming_problem"], [191, "https://github.com/Jung-Woo-sik/PyTorch-FastCampus"]], "repos_lang": {"HTML": "c100 p24 big green", "Python": "c100 p24 big green", "JavaScript": "c100 p20 big orange", "CSS": "c100 p12 big orange", "C": "c100 p12 big orange", "C#": "c100 p8 big green"}, "repos_topic": {"algorithms": 1, "programming": 1}, "user_event": {"WatchEvent": 6, "PushEvent": 15, "PullRequestEvent": 2, "CreateEvent": 6}}